gymie/__init__.py
gymie/__main__.py
gymie/api.py
gymie/exceptions.py
gymie/server.py
gymie-0.5.4.dist-info/LICENSE
gymie-0.5.4.dist-info/METADATA
gymie-0.5.4.dist-info/WHEEL
gymie-0.5.4.dist-info/top_level.txt
gymie-0.5.4.dist-info/RECORD
