Metadata-Version: 2.1
Name: gymie
Version: 0.5.4
Summary: WebSocket server that exposes an API to train AI agents on OpenAI Gym and gym-api-like Environments
Home-page: https://github.com/jscriptcoder/Gymie-Server
Author: Francisco Ramos
Author-email: francisco.ramos@researchlab.ai
License: UNKNOWN
Platform: UNKNOWN
Classifier: Programming Language :: Python :: 3.6
Classifier: License :: OSI Approved :: MIT License
Classifier: Operating System :: OS Independent
Requires-Python: >=3.6
Requires-Dist: eventlet (==0.28.0)
Requires-Dist: gym (==0.17.3)
Requires-Dist: uuid (==1.30)
Provides-Extra: box2d
Requires-Dist: box2d-py (==2.3.8) ; extra == 'box2d'
Provides-Extra: retro
Requires-Dist: gym-retro (==0.8.0) ; extra == 'retro'
Provides-Extra: unity
Requires-Dist: mlagents-envs (==0.20.0) ; extra == 'unity'
Requires-Dist: gym-unity (==0.20.0) ; extra == 'unity'
